kedro_softfail_runner/__init__.py
kedro_softfail_runner/_modidx.py
kedro_softfail_runner/core.py
kedro_softfail_runner-0.0.3.dist-info/LICENSE
kedro_softfail_runner-0.0.3.dist-info/METADATA
kedro_softfail_runner-0.0.3.dist-info/WHEEL
kedro_softfail_runner-0.0.3.dist-info/entry_points.txt
kedro_softfail_runner-0.0.3.dist-info/top_level.txt
kedro_softfail_runner-0.0.3.dist-info/RECORD
